rddl_verify/__init__.py
rddl_verify/app/__init__.py
rddl_verify/app/hash_data.py
rddl_verify/app/verify_signature.py
rddl_verify/main.py
rddl_verify/models/__init__.py
rddl_verify/models/validation_result.py
rddl_verify/routers/__init__.py
rddl_verify/routers/hash_data.py
rddl_verify/routers/validate_content.py
rddl_verify-0.2.0.dist-info/LICENSE
rddl_verify-0.2.0.dist-info/METADATA
rddl_verify-0.2.0.dist-info/WHEEL
rddl_verify-0.2.0.dist-info/RECORD
