Metadata-Version: 2.1
Name: rddl-verify
Version: 0.2.0
Summary: 
License: AGPL
Author: Jürgen Eckel
Author-email: juergen@riddleandcode.com
Requires-Python: >=3.10,<4.0
Classifier: License :: Other/Proprietary License
Classifier: Programming Language :: Python :: 3
Classifier: Programming Language :: Python :: 3.10
Classifier: Programming Language :: Python :: 3.11
Requires-Dist: fastapi (>=0.95.1,<0.96.0)
Requires-Dist: httpx (>=0.24.0,<0.25.0)
Requires-Dist: pydantic (>=1.10.7,<2.0.0)
Requires-Dist: python-decouple (>=3.8,<4.0)
Requires-Dist: python-multipart (>=0.0.6,<0.0.7)
Requires-Dist: uvicorn (>=0.22.0,<0.23.0)
Requires-Dist: wallycore (>=0.8.9,<0.9.0)
